odoo/addons/mrp_bom_structure_xlsx/README.rst
odoo/addons/mrp_bom_structure_xlsx/__init__.py
odoo/addons/mrp_bom_structure_xlsx/__manifest__.py
odoo/addons/mrp_bom_structure_xlsx/i18n/de.po
odoo/addons/mrp_bom_structure_xlsx/i18n/it.po
odoo/addons/mrp_bom_structure_xlsx/i18n/mrp_bom_structure_xlsx.pot
odoo/addons/mrp_bom_structure_xlsx/readme/CONTRIBUTORS.md
odoo/addons/mrp_bom_structure_xlsx/readme/DESCRIPTION.md
odoo/addons/mrp_bom_structure_xlsx/readme/INSTALL.md
odoo/addons/mrp_bom_structure_xlsx/readme/USAGE.md
odoo/addons/mrp_bom_structure_xlsx/report/__init__.py
odoo/addons/mrp_bom_structure_xlsx/report/bom_structure_xlsx.py
odoo/addons/mrp_bom_structure_xlsx/report/bom_structure_xlsx.xml
odoo/addons/mrp_bom_structure_xlsx/static/description/icon.png
odoo/addons/mrp_bom_structure_xlsx/static/description/index.html
odoo/addons/mrp_bom_structure_xlsx/tests/__init__.py
odoo/addons/mrp_bom_structure_xlsx/tests/common.py
odoo/addons/mrp_bom_structure_xlsx/tests/test_mrp_bom_structure_xlsx.py
odoo_addon_mrp_bom_structure_xlsx-18.0.1.0.0.2.dist-info/METADATA
odoo_addon_mrp_bom_structure_xlsx-18.0.1.0.0.2.dist-info/WHEEL
odoo_addon_mrp_bom_structure_xlsx-18.0.1.0.0.2.dist-info/top_level.txt
odoo_addon_mrp_bom_structure_xlsx-18.0.1.0.0.2.dist-info/RECORD
