Metadata-Version: 2.1
Name: odoo-addon-mrp_bom_structure_xlsx
Version: 18.0.1.0.0.2
Requires-Python: >=3.10
Requires-Dist: odoo-addon-report_xlsx==18.0.*
Requires-Dist: odoo==18.0.*
Summary: Export BoM Structure to Excel .XLSX
Home-page: https://github.com/OCA/manufacture-reporting
License: AGPL-3
Author: ForgeFlow, Odoo Community Association (OCA)
Author-email: support@odoo-community.org
Classifier: Programming Language :: Python
Classifier: Framework :: Odoo
Classifier: Framework :: Odoo :: 18.0
Classifier: License :: OSI Approved :: GNU Affero General Public License v3
